pythonRSC/__init__.py
pythonRSC/assembler.py
pythonRSC/classes.py
pythonRSC/cli.py
pythonRSC/emulator.py
pythonRSC-1.2.3.dist-info/LICENSE
pythonRSC-1.2.3.dist-info/METADATA
pythonRSC-1.2.3.dist-info/WHEEL
pythonRSC-1.2.3.dist-info/entry_points.txt
pythonRSC-1.2.3.dist-info/top_level.txt
pythonRSC-1.2.3.dist-info/RECORD
