Metadata-Version: 2.1
Name: pythonRSC
Version: 1.2.3
Summary: An emulator for the RSC architecture written in Python.
Author-email: Calastrophe <vmxoperation@proton.me>
Project-URL: Homepage, https://github.com/Calastrophe/pythonRSC
Project-URL: Bug Tracker, https://github.com/Calastrophe/pythonRSC/issues
Classifier: Programming Language :: Python :: 3.10
Classifier: License :: OSI Approved :: GNU General Public License v3 (GPLv3)
Classifier: Operating System :: OS Independent
Requires-Python: >=3.10
License-File: LICENSE
Requires-Dist: numpy
Requires-Dist: pythonCFG
